pg_statviz/__init__.py
pg_statviz/pg_statviz.py
pg_statviz/libs/NotoSans-Regular.ttf
pg_statviz/libs/NotoSans-SemiBold.ttf
pg_statviz/libs/__init__.py
pg_statviz/libs/dbconn.py
pg_statviz/libs/info.py
pg_statviz/libs/pg_statviz.png
pg_statviz/libs/pg_statviz_hires.png
pg_statviz/libs/pg_statviz_localhost_5432_buf.png
pg_statviz/libs/pg_statviz_localhost_5432_buf_rate.png
pg_statviz/libs/plot.py
pg_statviz/modules/__init__.py
pg_statviz/modules/analyze.py
pg_statviz/modules/buf.py
pg_statviz/modules/cache.py
pg_statviz/modules/checkp.py
pg_statviz/modules/conn.py
pg_statviz/modules/io.py
pg_statviz/modules/lock.py
pg_statviz/modules/tuple.py
pg_statviz/modules/wait.py
pg_statviz/modules/wal.py
pg_statviz/modules/xact.py
pg_statviz/tests/__init__.py
pg_statviz/tests/test_buf.py
pg_statviz/tests/test_cache.py
pg_statviz/tests/test_checkp.py
pg_statviz/tests/test_io.py
pg_statviz/tests/test_wal.py
pg_statviz/tests/util.py
pg_statviz-0.8.dist-info/licenses/LICENSE
pg_statviz-0.8.dist-info/METADATA
pg_statviz-0.8.dist-info/WHEEL
pg_statviz-0.8.dist-info/entry_points.txt
pg_statviz-0.8.dist-info/top_level.txt
pg_statviz-0.8.dist-info/RECORD
