Metadata-Version: 2.4
Name: pg_statviz
Version: 0.8
Summary: A minimalist extension and utility pair for time series analysis and visualization of PostgreSQL internal statistics.
Author-email: Jimmy Angelakos <vyruss@hellug.gr>
License: pg_statviz
Project-URL: Homepage, https://github.com/vyruss/pg_statviz
Keywords: open-source,postgres,opensource,database,dataviz,time-series,postgresql,data-visualization,database-management,database-administration,performance-analysis,postgresql-database,postgresql-extension,time-series-analysis
Classifier: Development Status :: 4 - Beta
Classifier: License :: OSI Approved :: PostgreSQL License
Classifier: Programming Language :: Python :: 3
Requires-Python: >=3.11
License-File: LICENSE
Requires-Dist: argh
Requires-Dist: contourpy
Requires-Dist: cycler
Requires-Dist: fonttools
Requires-Dist: kiwisolver
Requires-Dist: matplotlib
Requires-Dist: numpy
Requires-Dist: packaging
Requires-Dist: pandas
Requires-Dist: Pillow
Requires-Dist: psycopg
Requires-Dist: pyparsing
Requires-Dist: python-dateutil
Requires-Dist: six
Dynamic: license-file
